meltano_state_backend_snowflake/__init__.py
meltano_state_backend_snowflake/backend.py
meltano_state_backend_snowflake/py.typed
meltano_state_backend_snowflake-0.1.0.dist-info/METADATA
meltano_state_backend_snowflake-0.1.0.dist-info/WHEEL
meltano_state_backend_snowflake-0.1.0.dist-info/entry_points.txt
meltano_state_backend_snowflake-0.1.0.dist-info/licenses/LICENSE
meltano_state_backend_snowflake-0.1.0.dist-info/RECORD
