Metadata-Version: 2.4
Name: meltano-state-backend-snowflake
Version: 0.1.0
Summary: Meltano State Backend for Snowflake
Author-email: Taylor Murphy <taylor@arch.dev>
License-Expression: MIT
License-File: LICENSE
Classifier: Programming Language :: Python :: 3 :: Only
Classifier: Programming Language :: Python :: 3.9
Classifier: Programming Language :: Python :: 3.10
Classifier: Programming Language :: Python :: 3.11
Classifier: Programming Language :: Python :: 3.12
Classifier: Programming Language :: Python :: 3.13
Requires-Python: >=3.9
Requires-Dist: meltano>=3.7
Requires-Dist: snowflake-connector-python<4,>=3
